bmitest.py
chulleeBmiTest/bmitest.py
chulleeBmiTest-0.0.0.1.dist-info/METADATA
chulleeBmiTest-0.0.0.1.dist-info/WHEEL
chulleeBmiTest-0.0.0.1.dist-info/top_level.txt
chulleeBmiTest-0.0.0.1.dist-info/RECORD
